vgrid/__init__.py
vgrid/binning/__init__.py
vgrid/binning/a5bin.py
vgrid/binning/dggalbin.py
vgrid/binning/digipinbin.py
vgrid/binning/geohashbin.py
vgrid/binning/h3bin.py
vgrid/binning/isea4tbin.py
vgrid/binning/olcbin.py
vgrid/binning/polygonbin.py
vgrid/binning/qtmbin.py
vgrid/binning/quadkeybin.py
vgrid/binning/rhealpixbin.py
vgrid/binning/s2bin.py
vgrid/binning/tilecodebin.py
vgrid/conversion/__init__.py
vgrid/conversion/latlon2dggs.py
vgrid/conversion/dggs2geo/__init__.py
vgrid/conversion/dggs2geo/a52geo.py
vgrid/conversion/dggs2geo/dggal2geo.py
vgrid/conversion/dggs2geo/dggrid2geo.py
vgrid/conversion/dggs2geo/digipin2geo.py
vgrid/conversion/dggs2geo/ease2geo.py
vgrid/conversion/dggs2geo/gars2geo.py
vgrid/conversion/dggs2geo/geohash2geo.py
vgrid/conversion/dggs2geo/georef2geo.py
vgrid/conversion/dggs2geo/h32geo.py
vgrid/conversion/dggs2geo/isea3h2geo.py
vgrid/conversion/dggs2geo/isea4t2geo.py
vgrid/conversion/dggs2geo/maidenhead2geo.py
vgrid/conversion/dggs2geo/mgrs2geo.py
vgrid/conversion/dggs2geo/olc2geo.py
vgrid/conversion/dggs2geo/qtm2geo.py
vgrid/conversion/dggs2geo/quadkey2geo.py
vgrid/conversion/dggs2geo/rhealpix2geo.py
vgrid/conversion/dggs2geo/s22geo.py
vgrid/conversion/dggs2geo/tilecode2geo.py
vgrid/conversion/dggscompact/__init__.py
vgrid/conversion/dggscompact/a5compact.py
vgrid/conversion/dggscompact/dggalcompact.py
vgrid/conversion/dggscompact/digipincompact.py
vgrid/conversion/dggscompact/easecompact.py
vgrid/conversion/dggscompact/geohashcompact.py
vgrid/conversion/dggscompact/h3compact.py
vgrid/conversion/dggscompact/isea3hcompact.py
vgrid/conversion/dggscompact/isea4tcompact.py
vgrid/conversion/dggscompact/olccompact.py
vgrid/conversion/dggscompact/qtmcompact.py
vgrid/conversion/dggscompact/quadkeycompact.py
vgrid/conversion/dggscompact/rhealpixcompact.py
vgrid/conversion/dggscompact/s2compact.py
vgrid/conversion/dggscompact/tilecodecompact.py
vgrid/conversion/raster2dggs/__init__.py
vgrid/conversion/raster2dggs/raster2a5.py
vgrid-1.4.10.dist-info/METADATA
vgrid-1.4.10.dist-info/WHEEL
vgrid-1.4.10.dist-info/entry_points.txt
vgrid-1.4.10.dist-info/licenses/LICENSE
vgrid-1.4.10.dist-info/RECORD
