Metadata-Version: 2.4
Name: vgrid
Version: 1.4.10
Summary: Vgrid - DGGS and Cell-based Geocoding Utilites
Project-URL: Homepage, https://github.com/opengeospatial/vgrid
Author-email: Thang Quach <quachdongthang@gmail.com>
License: MIT
License-File: LICENSE
Keywords: Cell-based Geocoding,DGGS,Vgrid
Requires-Python: <3.14,>=3.9
Requires-Dist: dggal~=0.0.6
Requires-Dist: dggrid4py>=0.5.2
Requires-Dist: ease-dggs>=0.1.0
Requires-Dist: fiona
Requires-Dist: future
Requires-Dist: gars-field>=0.3.3
Requires-Dist: gdown
Requires-Dist: geopandas
Requires-Dist: h3>=4.3.1
Requires-Dist: matplotlib
Requires-Dist: pya5>=0.6.1
Requires-Dist: pyarrow
Requires-Dist: rasterio
Requires-Dist: requests
Requires-Dist: scipy
Requires-Dist: seaborn>=0.13.2
Requires-Dist: shapely>=2.0.7
Requires-Dist: tqdm>=4.67.1
Provides-Extra: dev
Requires-Dist: pytest-cov>=4.0.0; extra == 'dev'
Requires-Dist: pytest>=7.0.0; extra == 'dev'
